{"GlobalPropertiesHash":"ytaOOeDgyF1YNCgAbg7VJ7/ITOxXwfDbFxWotaLklIM=","FingerprintPatternsHash":"gq3WsqcKBUGTSNle7RKKyXRIwh7M8ccEqOqYvIzoM04=","PropertyOverridesHash":"8ZRc1sGeVrPBx4lD717BgRaQekyh78QKV9SKsdt638U=","InputHashes":["qLBUnBh1hKxCBGmPfDiMYyUTFBfPN77dzKbNS4rhgmg=","ZIXuDsdSDyI0QpFVgsB/9kNtfagFDPtn\u002B1lr\u002BIh7Ij0=","pVBPPR2Ls79y9VCTo/SDhGdHHt1OVgYDydZ4ZbRut9U="],"CachedAssets":{"qLBUnBh1hKxCBGmPfDiMYyUTFBfPN77dzKbNS4rhgmg=":{"Identity":"D:\\VS projects\\Module 1 DSA\\CityNavigation\\wwwroot\\Index.html","SourceId":"CityNavigation","SourceType":"Discovered","ContentRoot":"D:\\VS projects\\Module 1 DSA\\CityNavigation\\wwwroot\\","BasePath":"_content/CityNavigation","RelativePath":"Index#[.{fingerprint}]?.html","AssetKind":"All","AssetMode":"All","AssetRole":"Primary","AssetMergeBehavior":null,"AssetMergeSource":"","RelatedAsset":null,"AssetTraitName":null,"AssetTraitValue":null,"Fingerprint":"ns03n2vbxf","Integrity":"OWpuVmCaLeXHT0jUAJl6Gst7AW6NStoJgI8SdPFyBvg=","CopyToOutputDirectory":"Never","CopyToPublishDirectory":"PreserveNewest","OriginalItemSpec":"wwwroot\\Index.html","FileLength":37460,"LastWriteTime":"2026-02-19T14:26:32.6968647+00:00"}},"CachedCopyCandidates":{}}